{
  "schema_version": "1",
  "open_source": true,
  "model_name": "poker44-flow-detector",
  "model_version": "1",
  "framework": "mlp",
  "license": "MIT",
  "repo_url": "https://github.com/samie888/poker_run4",
  "repo_commit": "",
  "artifact_sha256": "32a79452da582e58015ac59c14342d697e3ce4675324c03a4e87f2f83bfd6056",
  "artifact_basename": "current.joblib",
  "implementation_sha256": "e6399fa8d982ee7a604c8d62a19e03f4cfbd3ea9c5145459196d024336dbaa15",
  "implementation_files": [
    "neurons/miner.py",
    "poker44_ml/inference.py",
    "poker44_ml/features.py",
    "poker44_ml/sequence_model.py",
    "poker44_ml/stacked.py",
    "poker44_ml/calibration.py",
    "poker44_ml/batch_calibration.py",
    "poker44/validator/payload_view.py"
  ],
  "inference_mode": "local-joblib",
  "training_data_statement": "Trained on the Poker44 public training benchmark (api.poker44.net). No validator-private evaluation data used.",
  "training_data_sources": [
    "released_training_benchmark"
  ],
  "private_data_attestation": "No validator-private data used. Supervised artifacts use released benchmark labels only.",
  "data_attestation": "No validator-private data used. Supervised artifacts use released benchmark labels only."
}
